findcoord/__init__.py
findcoord/transform.py
tests/test_basic.py
findcoord-0.2.0.dist-info/LICENSE
findcoord-0.2.0.dist-info/METADATA
findcoord-0.2.0.dist-info/WHEEL
findcoord-0.2.0.dist-info/top_level.txt
findcoord-0.2.0.dist-info/RECORD
